foliant/preprocessors/replace.py
foliantcontrib.replace-2.0.0.dist-info/LICENSE
foliantcontrib.replace-2.0.0.dist-info/METADATA
foliantcontrib.replace-2.0.0.dist-info/WHEEL
foliantcontrib.replace-2.0.0.dist-info/top_level.txt
foliantcontrib.replace-2.0.0.dist-info/RECORD
