Metadata-Version: 2.1
Name: foliantcontrib.replace
Version: 2.0.0
Summary: Replace text by dictionary.
Home-page: https://github.com/foliant-docs/foliantcontrib.replace
Author: Anton Bukhtiyarov
Author-email: apkraft@gmail.com
License: MIT
Platform: any
Classifier: Development Status :: 5 - Production/Stable
Classifier: Environment :: Console
Classifier: Intended Audience :: Developers
Classifier: License :: OSI Approved :: MIT License
Classifier: Operating System :: OS Independent
Classifier: Programming Language :: Python
Classifier: Topic :: Documentation
Classifier: Topic :: Utilities
License-File: LICENSE
Requires-Dist: foliant (>=1.0.8)
Requires-Dist: foliantcontrib.utils (>=1.0.3)
